volumetric/__init__.py
volumetric/__main__.py
volumetric/fs_routes.py
volumetric/snippets/__init__.py
volumetric/snippets/conditionals.py
volumetric/snippets/error_handling.py
volumetric/snippets/javascript.py
volumetric/snippets/structure.py
volumetric/xml_helpers.py
volumetric_flask-1.0.0.dist-info/entry_points.txt
volumetric_flask-1.0.0.dist-info/LICENSE
volumetric_flask-1.0.0.dist-info/METADATA
volumetric_flask-1.0.0.dist-info/WHEEL
volumetric_flask-1.0.0.dist-info/RECORD
